markyp_highlightjs/__init__.py
markyp_highlightjs-0.1910.0.dist-info/LICENSE
markyp_highlightjs-0.1910.0.dist-info/METADATA
markyp_highlightjs-0.1910.0.dist-info/WHEEL
markyp_highlightjs-0.1910.0.dist-info/top_level.txt
markyp_highlightjs-0.1910.0.dist-info/RECORD
