Metadata-Version: 2.1
Name: markyp-highlightjs
Version: 0.1910.0
Summary: Highlight.js-based syntax highlighting for web pages built with markyp-html
Home-page: https://github.com/volfpeter/markyp-highlightjs
Author: Peter Volf
Author-email: do.volfp@gmail.com
License: MIT
Keywords: html markup generator utility syntax code highlighting
Platform: UNKNOWN
Classifier: Development Status :: 5 - Production/Stable
Classifier: Intended Audience :: Developers
Classifier: License :: OSI Approved :: MIT License
Classifier: Natural Language :: English
Classifier: Operating System :: OS Independent
Classifier: Programming Language :: Python :: 3 :: Only
Classifier: Programming Language :: Python :: 3.6
Classifier: Programming Language :: Python :: 3.7
Classifier: Programming Language :: Python :: 3.8
Classifier: Topic :: Internet :: WWW/HTTP :: Dynamic Content
Classifier: Topic :: Software Development :: Code Generators
Classifier: Topic :: Software Development :: Libraries :: Python Modules
Classifier: Topic :: Text Processing :: Markup :: HTML
Classifier: Topic :: Utilities
Classifier: Typing :: Typed
Requires-Python: >=3.6
Requires-Dist: markyp-html (>=0.1910)
Requires-Dist: markyp (>=0.1910)
